migracraft/__init__.py
migracraft/config.py
migracraft/entity_generator.py
migracraft/exceptions.py
migracraft/main.py
migracraft/migracraft.py
migracraft/migration_manager.py
migracraft/sql_generator.py
migracraft/validator.py
migracraft-1.0.0.dist-info/licenses/LICENSE
tests/__init__.py
tests/conftest.py
tests/test_differential.py
tests/test_differential_migration.py
tests/test_entity_generation.py
tests/test_foreign_keys.py
tests/test_rollback.py
tests/test_rollback_migration.py
tests/test_schema_validation.py
tests/test_validation.py
migracraft-1.0.0.dist-info/METADATA
migracraft-1.0.0.dist-info/WHEEL
migracraft-1.0.0.dist-info/entry_points.txt
migracraft-1.0.0.dist-info/top_level.txt
migracraft-1.0.0.dist-info/RECORD
