Metadata-Version: 2.4
Name: migracraft
Version: 1.0.0
Summary: Craft perfect PostgreSQL migrations from YAML schema definitions with multi-language entity generation
Home-page: https://github.com/carmonac/migracraft
Author: Carlos Merchán Carmona
Author-email: ccarmona.87@outlook.es
Project-URL: Bug Reports, https://github.com/carmonac/migracraft/issues
Project-URL: Source, https://github.com/carmonac/migracraft
Project-URL: Documentation, https://github.com/carmonac/migracraft#readme
Keywords: postgresql,database,migration,schema,yaml,generator,entity,sql,differential,craft
Classifier: Development Status :: 4 - Beta
Classifier: Intended Audience :: Developers
Classifier: License :: OSI Approved :: MIT License
Classifier: Operating System :: OS Independent
Classifier: Programming Language :: Python :: 3
Classifier: Programming Language :: Python :: 3.8
Classifier: Programming Language :: Python :: 3.9
Classifier: Programming Language :: Python :: 3.10
Classifier: Programming Language :: Python :: 3.11
Classifier: Programming Language :: Python :: 3.12
Classifier: Topic :: Database
Classifier: Topic :: Software Development :: Code Generators
Classifier: Topic :: Software Development :: Libraries :: Python Modules
Classifier: Environment :: Console
Requires-Python: >=3.8
License-File: LICENSE
Requires-Dist: PyYAML>=6.0.0
Provides-Extra: dev
Requires-Dist: pytest>=8.0.0; extra == "dev"
Requires-Dist: pytest-cov>=6.0.0; extra == "dev"
Provides-Extra: test
Requires-Dist: pytest>=8.0.0; extra == "test"
Requires-Dist: pytest-cov>=6.0.0; extra == "test"
Dynamic: author
Dynamic: author-email
Dynamic: classifier
Dynamic: description
Dynamic: description-content-type
Dynamic: home-page
Dynamic: keywords
Dynamic: license-file
Dynamic: project-url
Dynamic: provides-extra
Dynamic: requires-dist
Dynamic: requires-python
Dynamic: summary
